AUTHORS.rst
CONTRIBUTING.rst
HISTORY.rst
LICENSE
MANIFEST.in
README.rst
setup.cfg
setup.py
docs/Makefile
docs/authors.rst
docs/conf.py
docs/contributing.rst
docs/history.rst
docs/index.rst
docs/installation.rst
docs/make.bat
docs/readme.rst
docs/usage.rst
mpipso/__init__.py
mpipso/mpipso.py
mpipso/pso.py
mpipso.egg-info/PKG-INFO
mpipso.egg-info/SOURCES.txt
mpipso.egg-info/dependency_links.txt
mpipso.egg-info/not-zip-safe
mpipso.egg-info/top_level.txt
tests/__init__.py
tests/test_mpipso.py
tests/test_pso.py