Metadata-Version: 1.2
Name: mpipso
Version: 0.1.0
Summary: MPI compatibel Particle Swarm Optimization
Home-page: https://github.com/sibirrer/mpipso
Author: Simon Birrer
Author-email: sibirrer@gmail.com
License: MIT license
Keywords: mpipso
Platform: UNKNOWN
Classifier: Development Status :: 2 - Pre-Alpha
Classifier: Intended Audience :: Developers
Classifier: License :: OSI Approved :: MIT License
Classifier: Natural Language :: English
Classifier: Programming Language :: Python :: 3
Classifier: Programming Language :: Python :: 3.5
Classifier: Programming Language :: Python :: 3.6
Classifier: Programming Language :: Python :: 3.7
Classifier: Programming Language :: Python :: 3.8
Requires-Python: >=3.5
